gamma/__init__.py
gamma/base.py
gamma/errors.py
gamma/models.py
gamma/table.py
gamma_kit-0.1.dist-info/METADATA
gamma_kit-0.1.dist-info/WHEEL
gamma_kit-0.1.dist-info/top_level.txt
gamma_kit-0.1.dist-info/RECORD
